[
  {
    "created": "2024-11-11T05:42:18.180Z",
    "updated": "2024-11-11T05:42:18.180Z",
    "id": 1364363,
    "title": "Срочно",
    "sort_order": 1.3749326177082057,
    "row_count": 1,
    "board_id": 1107759,
    "wip_limit": null,
    "wip_limit_type": 1,
    "default_tags": null,
    "last_moved_warning_after_days": -1,
    "external_id": null,
    "default_card_type_id": null,
    "last_moved_warning_after_hours": -1,
    "condition": 1,
    "last_moved_warning_after_minutes": -1,
    "uid": "a8d47684-6557-4e6b-8385-51b22224fbca",
    "locked": null
  },
  {
    "created": "2024-11-11T05:42:18.180Z",
    "updated": "2024-11-11T05:42:18.180Z",
    "id": 1364364,
    "title": "К дате",
    "sort_order": 3.1030892971832693,
    "row_count": 1,
    "board_id": 1107759,
    "wip_limit": null,
    "wip_limit_type": 1,
    "default_tags": null,
    "last_moved_warning_after_days": -1,
    "external_id": null,
    "default_card_type_id": null,
    "last_moved_warning_after_hours": -1,
    "condition": 1,
    "last_moved_warning_after_minutes": -1,
    "uid": "dd2fb9c6-b0f9-4f14-ac70-e37cfe3cad54",
    "locked": null
  },
  {
    "created": "2024-11-11T05:42:18.180Z",
    "updated": "2024-11-11T05:42:18.180Z",
    "id": 1364365,
    "title": "Стандартные",
    "sort_order": 4.629268180164839,
    "row_count": 1,
    "board_id": 1107759,
    "wip_limit": null,
    "wip_limit_type": 1,
    "default_tags": null,
    "last_moved_warning_after_days": -1,
    "external_id": null,
    "default_card_type_id": null,
    "last_moved_warning_after_hours": -1,
    "condition": 1,
    "last_moved_warning_after_minutes": -1,
    "uid": "0ceeaec4-8d3c-47a9-ab72-ff532ccae329",
    "locked": null
  },
  {
    "created": "2024-11-11T05:42:18.180Z",
    "updated": "2024-11-11T05:42:18.180Z",
    "id": 1364366,
    "title": "Нематериальные",
    "sort_order": 6.61319087368233,
    "row_count": 1,
    "board_id": 1107759,
    "wip_limit": null,
    "wip_limit_type": 1,
    "default_tags": null,
    "last_moved_warning_after_days": -1,
    "external_id": null,
    "default_card_type_id": null,
    "last_moved_warning_after_hours": -1,
    "condition": 1,
    "last_moved_warning_after_minutes": -1,
    "uid": "a0e94d1a-d19c-44f9-baaf-57bb4c02f04a",
    "locked": null
  }
]